[
  {
    "id": 1755940893041,
    "image": "/uploads/home/exclusive/1755940893040.png",
    "titleLine": "Student Discounts on Softwares & Equipments"
  },
  {
    "id": 1755940908632,
    "image": "/uploads/home/exclusive/1755940908630.png",
    "titleLine": "Updated Ai Integrated Modules"
  },
  {
    "id": 1755940927655,
    "image": "/uploads/home/exclusive/1755940927635.png",
    "titleLine": "shoot a web series While Studying"
  },
  {
    "id": 1755940940239,
    "image": "/uploads/home/exclusive/1755940940236.png",
    "titleLine": "Authorised Industry Expert Mentors"
  },
  {
    "id": 1755940970220,
    "image": "/uploads/home/exclusive/1755940970218.png",
    "titleLine": "100% Placement"
  },
  {
    "id": 1755940983090,
    "image": "/uploads/home/exclusive/1755940983089.png",
    "titleLine": "Internship with Expert FilmMakers"
  },
  {
    "id": 1755940993312,
    "image": "/uploads/home/exclusive/1755940993310.png",
    "titleLine": "Film Shoots & VFX Studio Visits"
  },
  {
    "id": 1755941005865,
    "image": "/uploads/home/exclusive/1755941005864.png",
    "titleLine": "Unlimited Stock Assets Access"
  },
  {
    "id": 1755941025541,
    "image": "/uploads/home/exclusive/1755941025540.png",
    "titleLine": "Master Classes of Industry Experts"
  },
  {
    "id": 1755941040697,
    "image": "/uploads/home/exclusive/1755941040696.png",
    "titleLine": "Hands On Practical Approach"
  },
  {
    "id": 1755941055665,
    "image": "/uploads/home/exclusive/1755941055663.png",
    "titleLine": "Overseas FilmMaking Practice"
  },
  {
    "id": 1755941069018,
    "image": "/uploads/home/exclusive/1755941069016.png",
    "titleLine": "Extended Lab Access"
  }
]